{
 "standings": [
  {
   "lastAccept": 1590770226,
   "pos": 1,
   "score": 383,
   "taskStats": {
    "transcendence_rebellion": {
     "points": 383,
     "time": 1590770226
    }
   },
   "team": "Kuality"
  },
  {
   "lastAccept": 1590770267,
   "pos": 2,
   "score": 383,
   "taskStats": {
    "transcendence_rebellion": {
     "points": 383,
     "time": 1590770267
    }
   },
   "team": "OpenToAll"
  },
  {
   "lastAccept": 1590770287,
   "pos": 3,
   "score": 383,
   "taskStats": {
    "transcendence_rebellion": {
     "points": 383,
     "time": 1590770287
    }
   },
   "team": "RATF"
  },
  {
   "lastAccept": 1590770305,
   "pos": 4,
   "score": 383,
   "taskStats": {
    "transcendence_rebellion": {
     "points": 383,
     "time": 1590770305
    }
   },
   "team": "Ganesh"
  },
  {
   "lastAccept": 1590770323,
   "pos": 5,
   "score": 383,
   "taskStats": {
    "transcendence_rebellion": {
     "points": 383,
     "time": 1590770323
    }
   },
   "team": "isok_"
  },
  {
   "lastAccept": 1590770361,
   "pos": 6,
   "score": 383,
   "taskStats": {
    "transcendence_rebellion": {
     "points": 383,
     "time": 1590770361
    }
   },
   "team": "SSTI"
  },
  {
   "lastAccept": 1590770378,
   "pos": 7,
   "score": 383,
   "taskStats": {
    "transcendence_rebellion": {
     "points": 383,
     "time": 1590770378
    }
   },
   "team": "Benevolent_0rder_0f_4ntelopes"
  },
  {
   "lastAccept": 1590770403,
   "pos": 8,
   "score": 383,
   "taskStats": {
    "transcendence_rebellion": {
     "points": 383,
     "time": 1590770403
    }
   },
   "team": "justCatTheFish"
  }
 ],
 "tasks": [
  "transcendence_rebellion"
 ]
}